LICENSE
MANIFEST.in
requirements.txt
setup.py
bin/koucli
kou/__init__.py
kou/__main__.py
kou/koucmd.py
kou.egg-info/PKG-INFO
kou.egg-info/SOURCES.txt
kou.egg-info/dependency_links.txt
kou.egg-info/requires.txt
kou.egg-info/top_level.txt