Metadata-Version: 1.0
Name: kou
Version: 0.1.7
Summary: Kocaeli University OBS Command Line Interface
Home-page: https://github.com/burakkose/kou-obs-cli
Author: Burak Köse
Author-email: burakks41@gmail.com
License: The MIT License
Keywords: cli,kou,obs
Platform: OS Independent
